vdt.version-0.1.8-py3.10-nspkg.pth
vdt/version/__init__.py
vdt/version/main.py
vdt/version/repo.py
vdt/version/shared.py
vdt/version/utils.py
vdt.version-0.1.8.dist-info/LICENSE
vdt.version-0.1.8.dist-info/METADATA
vdt.version-0.1.8.dist-info/WHEEL
vdt.version-0.1.8.dist-info/entry_points.txt
vdt.version-0.1.8.dist-info/namespace_packages.txt
vdt.version-0.1.8.dist-info/top_level.txt
vdt.version-0.1.8.dist-info/zip-safe
vdt.version-0.1.8.dist-info/RECORD
